{
  "project_info": {
    "project_number": "341952964923",
    "firebase_url": "https://face-recognition-cd345.firebaseio.com",
    "project_id": "face-recognition-cd345",
    "storage_bucket": "face-recognition-cd345.appspot.com"
  },
  "client": [
    {
      "client_info": {
        "mobilesdk_app_id": "1:341952964923:android:d8900d9458eb00fdd52f1e",
        "android_client_info": {
          "package_name": "com.valmont"
        }
      },
      "oauth_client": [
        {
          "client_id": "341952964923-s6lilourr7clcg3j5coj16t5qmmko777.apps.googleusercontent.com",
          "client_type": 3
        }
      ],
      "api_key": [
        {
          "current_key": "AIzaSyAd58ad6Ad0yHGrmqbiga4KWuJurYJnaGM"
        }
      ],
      "services": {
        "appinvite_service": {
          "other_platform_oauth_client": [
            {
              "client_id": "341952964923-s6lilourr7clcg3j5coj16t5qmmko777.apps.googleusercontent.com",
              "client_type": 3
            }
          ]
        }
      }
    }
  ],
  "configuration_version": "1"
}